{
    "regular_rod": {
        "id": "R1",
        "unique": true,
        "display_name": "Regular Rod",
        "color": "#8C5B3D",
        "description": "Just a regular fishing rod made from softwood. Its your first rod so don't expect anything special.",
        "use": "Will allow you to start fishing for common fish!\nJust use `/fish` to fish, the highest available rod will be used.",
        "category": "rods",
        "emoji_id": "1205874083275874375",
        "price": 50,
        "max_count": 1,
        "data": {},
        "fish_count_till_available": 0
    },
    "earthworm_bait": {
        "id": "B1",
        "unique": false,
        "display_name": "Worm Bait",
        "color": "#73172D",
        "description": "Just a regular worm put on a hook. Won't do crazy things but still better than nothing.",
        "use": "Will give you a slightly higher chance to encounter higher-rarity fish. Only properly works if your rod is able to fish for anything more than common.",
        "category": "bait",
        "emoji_id": "1205919749759045692",
        "price": 10,
        "max_count": 100,
        "data": {}
    }
}